image_in_terminal-1.32.dist-info/licenses/LICENSE
imageinterminal/__init__.py
imageinterminal/constants.py
imageinterminal/custom_rich_help_formatter.py
imageinterminal/iit.py
imageinterminal/main.py
imageinterminal/utils.py
image_in_terminal-1.32.dist-info/METADATA
image_in_terminal-1.32.dist-info/WHEEL
image_in_terminal-1.32.dist-info/entry_points.txt
image_in_terminal-1.32.dist-info/top_level.txt
image_in_terminal-1.32.dist-info/RECORD
