Metadata-Version: 2.4
Name: image-in-terminal
Version: 1.32
Summary: Simple Python package to display a single or multiple images in the terminal by converting it into text
Home-page: https://github.com/odell0111/image-in-terminal
Author: Odell
Author-email: odellgm11012001@gmail.com
License: MIT License
Project-URL: Homepage, https://github.com/odell0111/image-in-terminal
Project-URL: Repository, https://github.com/odell0111/image-in-terminal
Keywords: terminal,image,imageonterminal,image-on-terminal,image on terminal,imageinterminal,image in terminal,imageonconsole,image-on-console,image on console,imageinconsole,image-in-console,image in console,imagetotext,image-to-text,image to text
Classifier: License :: OSI Approved :: MIT License
Classifier: Programming Language :: Python
Classifier: Programming Language :: Python :: 3
Classifier: Environment :: Console
Classifier: Operating System :: OS Independent
Requires-Python: >=3.9
License-File: LICENSE
Requires-Dist: rich
Requires-Dist: pytest
Requires-Dist: requests
Requires-Dist: pillow
Requires-Dist: argparse
Requires-Dist: rich-argparse
Dynamic: license-file
